digital-design-ips/GPIO/src/gpio_port.v
`timescale 1ns / 1ps

module gpio_port #(
    parameter WIDTH = 32
)(
    input  sys_clk,
    input  reset,   // active-high

    // MMIO
    input  w_en,
    input  r_en,
    input  [7:0]addr,
    input  [WIDTH-1:0] w_data,
    output reg  [WIDTH-1:0] r_data,
    
    // GPIO pad
    inout  [WIDTH-1:0] gpio_pin,
    
    //Interrupt
    output irq
);

    // Internal registers
    reg  [WIDTH-1:0] data_reg;
    reg  [WIDTH-1:0] dir_reg;
    reg  [WIDTH-1:0] gpio_in_reg;

    //Interrupt Register
    
    reg [WIDTH-1:0] prev_gpio;
    reg [WIDTH-1:0] i_status;
    reg [WIDTH-1:0] i_en;
    wire [WIDTH-1:0]edge_detect;

    // ---------------------------
    // GPIO pad connection
    // ---------------------------
    genvar i;
    generate
        for (i = 0; i < WIDTH; i = i + 1) begin : gpio_bits
            assign gpio_pin = dir_reg[i] ? data_reg[i] : 1'bz;
        end
    endgenerate

    //Rise and fall edge detect
    assign edge_detect = ((~prev_gpio) & gpio_in_reg) | (prev_gpio & (~gpio_in_reg));
    //edge_detect = (gpio_in_reg ^ prev_gpio);
    // ---------------------------
    // Input synchronization
    // ---------------------------
    always @(posedge sys_clk or posedge reset) begin
        if (reset) begin
            gpio_in_reg <= 0;
            prev_gpio <= 0;
        end else begin
            prev_gpio <= gpio_in_reg;
            gpio_in_reg <= gpio_pin;
        end
    end
    
    // ---------------------------
    // Interrupt logic (CORRECT)
    // ---------------------------
    always @(posedge sys_clk or posedge reset) begin
        if (reset) begin
            i_status <= 1'b0;
            i_en     <= 1'b0;
        end else begin
            // Hardware sets interrupt on edge (INPUT only)
            //Only when interrupt is enabled
            //Only when an edge occurs
            //Only when GPIO is INPUT
            //if (i_en && edge_detect && (dir_reg == 0))
            // i_status <= 1'b1;
            i_status <= i_status | (edge_detect & i_en & ~dir_reg);

            // Software clears interrupt (W1C)
            if (w_en && addr == 8'h10)
                i_status <= i_status & ~w_data; //(Masking)

            // Interrupt enable
            if (w_en && addr == 8'h08)
                i_en <= w_data;
        end
    end
    // ---------------------------
    // Write logic
    // ---------------------------
    always @(posedge sys_clk or posedge reset) begin
        if (reset) begin
            data_reg <= 0;
            dir_reg  <= 0;
        end else if (w_en) begin
            case (addr)
                8'h0: data_reg <= w_data; // DATA
                8'h4: dir_reg  <= w_data; // DIR
            endcase
        end
    end

    // ---------------------------
    // Read logic
    // ---------------------------
    always @(*) begin
        r_data = 0;
        if (r_en) begin
            case (addr)
                8'h0: r_data = data_reg;    // DATA
                8'h4: r_data = dir_reg;     // DIR
                8'h8: r_data = gpio_in_reg; // INPUT
//                8'h0C: r_data = {{(WIDTH-1){1'b0}}, i_status}; // INT_STATUS
                8'h0C: r_data = i_status;
                default: r_data = 0;
            endcase
        end
    end
    assign irq = |i_status;
endmodule

digital-design-ips/GPIO/sim/tb_gpio_port.v
`timescale 1ns / 1ps
module tb_gpio_port;
    parameter WIDTH = 32;
    reg sys_clk;
    reg reset;
    reg [7:0] addr;
    reg [31:0] w_data;
    reg w_en;
    reg r_en;
    wire [31:0] r_data;
    wire [31:0] gpio_pin;
    wire irq;

    // For driving input pins
    reg [WIDTH-1:0] gpio_drive;
    reg [WIDTH-1:0] gpio_oe;  // 0 = drive from TB, 1 = driven by DUT

    // Bidirectional modeling
    assign gpio_pin = gpio_oe ? {WIDTH{1'bz}} : gpio_drive;

    // Instantiate DUT
    gpio_port #(
        .WIDTH(WIDTH)
    ) dut (
        .sys_clk(sys_clk),
        .reset(reset),
        .w_en(w_en),
        .r_en(r_en),
        .addr(addr),
        .w_data(w_data),
        .r_data(r_data),
        .gpio_pin(gpio_pin),
        .irq(irq)
    );

    //Clock generation

    always #5 sys_clk =~sys_clk; //10ns  

    //--------------------------------------
    // Write Task
    //--------------------------------------
    task write_reg(input [7:0] a, input [31:0] data);
        begin
            @(posedge sys_clk);
            addr = a;
            w_data = data;
            w_en = 1;
            @(posedge sys_clk);
            w_en = 0;
        end
    endtask

    //--------------------------------------
    // Read Task
    //--------------------------------------
    task read_reg(input [7:0] a);
    begin
        @(posedge sys_clk);
        addr = a;
        r_en = 1;
        @(posedge sys_clk);
        $display("Read Addr %h = %h", a, r_data);
        r_en = 0;
    end
    endtask

    initial begin
        $display("GPIO Testbench");
        $dumpfile("GPIO_MMO.vcd");
        $dumpvars(0, tb_gpio_port);  // dump whole testbench hierarchy
        sys_clk = 0;
        reset = 1;
        w_en = 0;
        r_en = 0;
        addr = 0;
        w_data = 0;
        gpio_drive = 0;
        gpio_oe = 1;   // default input mode

        #20;
        reset = 0;

        //--------------------------------------
        // Configure GPIO[0] as OUTPUT
        //--------------------------------------
        write_reg(8'h04, 8'b0000_0001);  // DIR bit0 = 1
        #20;

        //--------------------------------------
        // Write DATA = 1 to GPIO[0]
        //--------------------------------------
        write_reg(8'h00, 8'b0000_0001);
        #20;
        //--------------------------------------
        // Generate edge on GPIO[1]
        //--------------------------------------
        read_reg(8'h08);
        gpio_oe = 0; // TB drives pin (input mode)
        gpio_drive = 8'b0000_0000;
        #20;

        gpio_drive = 8'b0000_0010; // Rising edge
        #20;

        //--------------------------------------
        // Check interrupt status
        //--------------------------------------
        read_reg(8'h0C);
        #50;
        $finish;
    end
endmodule

digital-design-ips/GPIO/sim/GPIO_MMO.vcd
$date
	Fri Feb 27 10:29:47 2026
$end
$version
	Icarus Verilog
$end
$timescale
	1ps
$end
$scope module tb_gpio_port $end
$var wire 32 ! gpio_pin [31:0] $end
$var wire 32 " r_data [31:0] $end
$var wire 1 # irq $end
$var parameter 32 $ WIDTH $end
$var reg 8 % addr [7:0] $end
$var reg 32 & gpio_drive [31:0] $end
$var reg 32 ' gpio_oe [31:0] $end
$var reg 1 ( r_en $end
$var reg 1 ) reset $end
$var reg 1 * sys_clk $end
$var reg 32 + w_data [31:0] $end
$var reg 1 , w_en $end
$scope module dut $end
$var wire 8 - addr [7:0] $end
$var wire 32 . edge_detect [31:0] $end
$var wire 32 / gpio_pin [31:0] $end
$var wire 1 ( r_en $end
$var wire 1 ) reset $end
$var wire 1 * sys_clk $end
$var wire 32 0 w_data [31:0] $end
$var wire 1 , w_en $end
$var wire 1 # irq $end
$var parameter 32 1 WIDTH $end
$var reg 32 2 data_reg [31:0] $end
$var reg 32 3 dir_reg [31:0] $end
$var reg 32 4 gpio_in_reg [31:0] $end
$var reg 32 5 i_en [31:0] $end
$var reg 32 6 i_status [31:0] $end
$var reg 32 7 prev_gpio [31:0] $end
$var reg 32 8 r_data [31:0] $end
$scope begin gpio_bits[0] $end
$var parameter 2 9 i $end
$upscope $end
$scope begin gpio_bits[1] $end
$var parameter 2 : i $end
$upscope $end
$scope begin gpio_bits[2] $end
$var parameter 3 ; i $end
$upscope $end
$scope begin gpio_bits[3] $end
$var parameter 3 < i $end
$upscope $end
$scope begin gpio_bits[4] $end
$var parameter 4 = i $end
$upscope $end
$scope begin gpio_bits[5] $end
$var parameter 4 > i $end
$upscope $end
$scope begin gpio_bits[6] $end
$var parameter 4 ? i $end
$upscope $end
$scope begin gpio_bits[7] $end
$var parameter 4 @ i $end
$upscope $end
$scope begin gpio_bits[8] $end
$var parameter 5 A i $end
$upscope $end
$scope begin gpio_bits[9] $end
$var parameter 5 B i $end
$upscope $end
$scope begin gpio_bits[10] $end
$var parameter 5 C i $end
$upscope $end
$scope begin gpio_bits[11] $end
$var parameter 5 D i $end
$upscope $end
$scope begin gpio_bits[12] $end
$var parameter 5 E i $end
$upscope $end
$scope begin gpio_bits[13] $end
$var parameter 5 F i $end
$upscope $end
$scope begin gpio_bits[14] $end
$var parameter 5 G i $end
$upscope $end
$scope begin gpio_bits[15] $end
$var parameter 5 H i $end
$upscope $end
$scope begin gpio_bits[16] $end
$var parameter 6 I i $end
$upscope $end
$scope begin gpio_bits[17] $end
$var parameter 6 J i $end
$upscope $end
$scope begin gpio_bits[18] $end
$var parameter 6 K i $end
$upscope $end
$scope begin gpio_bits[19] $end
$var parameter 6 L i $end
$upscope $end
$scope begin gpio_bits[20] $end
$var parameter 6 M i $end
$upscope $end
$scope begin gpio_bits[21] $end
$var parameter 6 N i $end
$upscope $end
$scope begin gpio_bits[22] $end
$var parameter 6 O i $end
$upscope $end
$scope begin gpio_bits[23] $end
$var parameter 6 P i $end
$upscope $end
$scope begin gpio_bits[24] $end
$var parameter 6 Q i $end
$upscope $end
$scope begin gpio_bits[25] $end
$var parameter 6 R i $end
$upscope $end
$scope begin gpio_bits[26] $end
$var parameter 6 S i $end
$upscope $end
$scope begin gpio_bits[27] $end
$var parameter 6 T i $end
$upscope $end
$scope begin gpio_bits[28] $end
$var parameter 6 U i $end
$upscope $end
$scope begin gpio_bits[29] $end
$var parameter 6 V i $end
$upscope $end
$scope begin gpio_bits[30] $end
$var parameter 6 W i $end
$upscope $end
$scope begin gpio_bits[31] $end
$var parameter 6 X i $end
$upscope $end
$upscope $end
$scope task read_reg $end
$var reg 8 Y a [7:0] $end
$upscope $end
$scope task write_reg $end
$var reg 8 Z a [7:0] $end
$var reg 32 [ data [31:0] $end
$upscope $end
$upscope $end
$enddefinitions $end
$comment Show the parameter values. $end
$dumpall
b11111 X
b11110 W
b11101 V
b11100 U
b11011 T
b11010 S
b11001 R
b11000 Q
b10111 P
b10110 O
b10101 N
b10100 M
b10011 L
b10010 K
b10001 J
b10000 I
b1111 H
b1110 G
b1101 F
b1100 E
b1011 D
b1010 C
b1001 B
b1000 A
b111 @
b110 ?
b101 >
b100 =
b11 <
b10 ;
b1 :
b0 9
b100000 1
b100000 $
$end
#0
$dumpvars
bx [
bx Z
bx Y
b0 8
b0 7
b0 6
b0 5
b0 4
b0 3
b0 2
b0 0
b0z /
b0 .
b0 -
0,
b0 +
0*
1)
0(
b1 '
b0 &
b0 %
0#
b0 "
b0z !
$end
#5000
1*
#10000
0*
#15000
1*
#20000
0*
b1 [
b100 Z
0)
#25000
b0 !
b0 /
b0x .
b1 3
b0z 4
1,
b1 +
b1 0
b100 %
b100 -
1*
#30000
0*
#35000
b0 4
b0z 7
0,
1*
#40000
0*
#45000
b0 .
b0 7
1*
#50000
0*
#55000
b1 !
b1 /
b1 2
1,
b0 %
b0 -
1*
b0 Z
#60000
0*
#65000
b1 .
b1 4
0,
1*
#70000
0*
#75000
b0 .
b1 7
1*
#80000
0*
#85000
b1 "
b1 8
1(
b1000 %
b1000 -
1*
b1000 Y
#90000
0*
#95000
b0x !
b0x /
b0 "
b0 8
b0 '
0(
1*
#100000
0*
#105000
b0x .
b0x 4
1*
#110000
0*
#115000
b0xx .
b0xx 4
b0x 7
b0xx !
b0xx /
1*
b10 &
#120000
0*
#125000
b0xx 7
1*
#130000
0*
#135000
1(
b1100 %
b1100 -
1*
b1100 Y
#140000
0*
#145000
0(
1*
